{
  "name": "award",
  "base": "PersistedModel",
  "idInjection": true,
  "options": {
    "validateUpsert": true
  },
  "scope": {},
  "properties": {
    "nameAr": {
      "type": "string",
      "required": false
    },
    "nameEn": {
      "type": "string",
      "required": false
    },
    "details": {
      "type": "string",
      "required": false
    },
    "from": {
      "type": "date",
      "required": true
    },
    "to": {
      "type": "date",
      "required": true
    },
    "occurrence": {
      "type": "number",
      "required": true
    },
    "occurrenceType": {
      "type": "string",
      "required": true ,
      "default" : "daily"
    },
    "countLimit": {
      "type": "number",
      "required": false,
      "default": 1
    },
    "clientTypes": {
      "type": [
        "string"
      ],
      "required": false,
      "default": []
    }
  },
  "validations": [],
  "relations": {
    "actionRelation": {
      "type": "embedsOne",
      "model": "awardAction",
      "property": "action",
      "options": {  
        "validate": true
      }
    },
    "periods": {
      "type": "hasMany",
      "model": "awardPeriod"
    },
    "couponTemplateRelation": {
      "type": "embedsMany",
      "model": "couponTemplate",
      "property": "coupons",
      "options": {
        "validate": true
      }
    },
    "areasRelation": {
      "type": "referencesMany",
      "model": "area",
      "foreignKey": "areaIds",
      "options": {
        "validate": true
      }
    },
    "prizesRelation": {
      "type": "embedsMany",
      "model": "productPrize",
      "property": "prizes",
      "options": {
        "validate": true
      }
    }
  },
  "acls": [],
  "methods": {}
}