{
  "name": "warehouse",
  "base": "PersistedModel",
  "idInjection": true,
  "options": {
    "validateUpsert": true
  },
  "scope" : { 
  },
  "properties": {
    "nameAr": {
      "type": "string",
      "required": true
    },
    "nameEn": {
      "type": "string",
      "required": true
    },
    "geo": {
      "type": "geopoint",
      "required": true
    }
  },
  "validations": [],
  "relations": {
    "warehouseProducts": {
      "type": "hasMany",
      "model": "warehouseProducts",
      "foreignKey": "warehouseId",
      "options": {
        "nestRemoting": true
      }
    }
  },
  "acls": [],
  "methods": {

    "logProducts": {
      "isStatic": true,
      "accepts": [
        
        {
          "arg": "id",
          "type": "string",
          "required": true,
          "description": "",
          "source": "path"
        }
        ,
        {
          "arg": "shift",
          "type": "number",
          "required": true,
          "source": "body"
        }
      ],
      "returns": [
        {
          "arg": "result",
          "type": "array",
          "root": true,
          "description": ""
        }
      ],
      "description": "",
      "http": [
        {
          "path": "/:id/log",
          "verb": "post"
        }
      ]
    }

  }
}
